Workbook

Sheet Cover
D4: VISTA ENERGY, S.A.B. de C.V.
D5: Integrated Financial Model · DCF & Comparable Valuation
D7: NYSE: VIST | BMV: VISTA | Oil & Gas E&P — Vaca Muerta, Argentina
B14: Prepared by: | D14: Andreas Santucci
B15: Date: | D15: June – July 2026
B16: Currency: | D16: US$ in thousands, unless otherwise noted
B17: Fiscal year end: | D17: December 31
B20: TABLE OF CONTENTS
B21: SHEET | D21: DESCRIPTION
B22: Outputs | D22: Operating & financial KPIs, valuation summary, DCF and sensitivity analysis.
B23: Model | D23: Integrated 3-statement model (Income Statement, Balance Sheet, Cash Flow), 2022A–2030E, with operating drivers.
B24: Imputs Drivers | D24: Forecast assumptions — Brent price scenarios (Best / Base / Worst) and production growth.
B25: Imput Historical | D25: Historical financials 2022–2025, sourced from SEC EDGAR 20-F filings (audited).
B28: COLOR LEGEND
B29: Blue = inputs / hardcoded assumptions
B30: Black = formulas / calculations
B31: Green = links to other worksheets
B32: Red = links to external files / sources
B33: Yellow fill = key assumption to review / update
B34: DATA SOURCES
B35: SEC EDGAR — Vista Energy Form 20-F (FY2022, FY2023, FY2025), audited financial statements. Market data as of June 2026.
B37: Disclaimer: Educational and illustrative purposes only; not investment advice or a recommendation.

Sheet Outputs
B3: OPERATIONAL METRICS
G5: 2022A | H5: 2023A | I5: 2024A | J5: 2025A | K5: 2026E | L5: 2027E | M5: 2028E | N5: 2029E | O5: 2030E
B7: Production | C7: boe/d | G7: =Model!G158 -> 48560 | H7: =Model!H158 -> 51149 | I7: =Model!I158 -> 69660 | J7: =Model!J158 -> 115479 | K7: =Model!K158 -> 132800.85 | L7: =Model!L158 -> 148736.95 | M7: =Model!M158 -> 163610.65 | N7: =Model!N158 -> 176699.5 | O7: =Model!O158 -> 187301.47
B8: Oil production | C8: bbl/d | H8: ='Imput Historical'!H232 -> 43287.671 | I8: ='Imput Historical'!I232 -> 60382.514 | J8: ='Imput Historical'!J232 -> 100000 | K8: =K7*'Imput Historical'!$J$234 -> 115000 | L8: =L7*'Imput Historical'!$J$234 -> 128800 | M8: =M7*'Imput Historical'!$J$234 -> 141680 | N8: =N7*'Imput Historical'!$J$234 -> 153014.4 | O8: =O7*'Imput Historical'!$J$234 -> 162195.26
B9: Gas & NGL production | C9: boe/d | H9: =H7-H8 -> 7861.3288 | I9: =I7-I8 -> 9277.4863 | J9: =J7-J8 -> 15479 | K9: =K7-K8 -> 17800.85 | L9: =L7-L8 -> 19936.952 | M9: =M7-M8 -> 21930.647 | N9: =N7-N8 -> 23685.099 | O9: =O7-O8 -> 25106.205
B10: Realized oil price | C10: $/bbl | G10: ='Imput Historical'!G219 -> 72.2 | H10: ='Imput Historical'!H219 -> 66.7 | I10: ='Imput Historical'!I219 -> 69.2 | J10: ='Imput Historical'!J219 -> 62.9 | K10: =Model!K156*('Imput Historical'!J219/'Imput Historical'!J218) -> 78.394428 | L10: =Model!L156*('Imput Historical'!$J$219/'Imput Historical'!$J$218) -> 75.627566 | M10: =Model!M156*('Imput Historical'!$J$219/'Imput Historical'!$J$218) -> 73.782991 | N10: =Model!N156*('Imput Historical'!$J$219/'Imput Historical'!$J$218) -> 71.938416 | O10: =Model!O156*('Imput Historical'!$J$219/'Imput Historical'!$J$218) -> 69.171554
B11: Lifting cost | C11: $/boe | G11: =Model!G157 -> 7.5 | H11: =Model!H157 -> 5.1 | I11: =Model!I157 -> 4.6 | J11: =Model!J157 -> 4.4 | K11: =Model!K157 -> 4.3 | L11: =Model!L157 -> 4.1 | M11: =Model!M157 -> 3.9 | N11: =Model!N157 -> 3.7 | O11: =Model!O157 -> 3.5
B12: Royalties & export duties | C12: $/boe | G12: =IFERROR(-Model!G13*1000/(G7*365),"") -> 10.645043 | H12: =IFERROR(-Model!H13*1000/(H7*365),"") -> 9.4707458 | I12: =IFERROR(-Model!I13*1000/(I7*365),"") -> 9.5945473 | J12: =IFERROR(-Model!J13*1000/(J7*365),"") -> 8.1933654 | K12: =IFERROR(-Model!K13*1000/(K7*365),"") -> 10.211672 | L12: =IFERROR(-Model!L13*1000/(L7*365),"") -> 9.8512605 | M12: =IFERROR(-Model!M13*1000/(M7*365),"") -> 9.6109858 | N12: =IFERROR(-Model!N13*1000/(N7*365),"") -> 9.3707112 | O12: =IFERROR(-Model!O13*1000/(O7*365),"") -> 9.0102992
B13: Selling expenses | C13: $/boe | G13: =IFERROR(-Model!G19*1000/(G7*365),"") -> 3.3797477 | H13: =IFERROR(-Model!H19*1000/(H7*365),"") -> 3.6847491 | I13: =IFERROR(-Model!I19*1000/(I7*365),"") -> 5.5193326 | J13: =IFERROR(-Model!J19*1000/(J7*365),"") -> 5.1737332 | K13: =IFERROR(-Model!K19*1000/(K7*365),"") -> 6.4482012 | L13: =IFERROR(-Model!L19*1000/(L7*365),"") -> 6.2206176 | M13: =IFERROR(-Model!M19*1000/(M7*365),"") -> 6.0688952 | N13: =IFERROR(-Model!N19*1000/(N7*365),"") -> 5.9171728 | O13: =IFERROR(-Model!O19*1000/(O7*365),"") -> 5.6895893
B14: Total cost per boe | C14: $/boe | G14: =IFERROR(G11+G12+G13,"") -> 21.524791 | H14: =IFERROR(H11+H12+H13,"") -> 18.255495 | I14: =IFERROR(I11+I12+I13,"") -> 19.71388 | J14: =IFERROR(J11+J12+J13,"") -> 17.767099 | K14: =IFERROR(K11+K12+K13,"") -> 20.959874 | L14: =IFERROR(L11+L12+L13,"") -> 20.171878 | M14: =IFERROR(M11+M12+M13,"") -> 19.579881 | N14: =IFERROR(N11+N12+N13,"") -> 18.987884 | O14: =IFERROR(O11+O12+O13,"") -> 18.199888
B15: EBITDA per boe | C15: $/boe | G15: =IFERROR(Model!G26*1000/(G7*365),"") -> 41.786013 | H15: =IFERROR(Model!H26*1000/(H7*365),"") -> 40.490193 | I15: =IFERROR(Model!I26*1000/(I7*365),"") -> 40.886891 | J15: =IFERROR(Model!J26*1000/(J7*365),"") -> 37.404417 | K15: =IFERROR(Model!K26*1000/(K7*365),"") -> 47.797925 | L15: =IFERROR(Model!L26*1000/(L7*365),"") -> 46.159561 | M15: =IFERROR(Model!M26*1000/(M7*365),"") -> 45.134519 | N15: =IFERROR(Model!N26*1000/(N7*365),"") -> 44.109477 | O15: =IFERROR(Model!O26*1000/(O7*365),"") -> 42.471113
B16: Net wells tied-in | C16: # | I16: ='Imput Historical'!I230 -> 50 | J16: ='Imput Historical'!J230 -> 74
B17: Oil / gas split and wells tied-in per FY2025 Form 20-F, which discloses 2023–2025 only. Forecast split holds the 2025 oil mix of 86.6% constant. Source data: Imput Historical rows 224–235.
B19: INCOME STATEMENT
G21: 2022A | H21: 2023A | I21: 2024A | J21: 2025A | K21: 2026E | L21: 2027E | M21: 2028E | N21: 2029E | O21: 2030E
B23: Revenue | C23: $M | G23: =Model!G7/1000 -> 1187.66 | H23: =Model!H7/1000 -> 1168.774 | I23: =Model!I7/1000 -> 1647.768 | J23: =Model!J7/1000 -> 2474.197 | K23: =Model!K7/1000 -> 3546.2281 | L23: =Model!L7/1000 -> 3831.5952 | M23: =Model!M7/1000 -> 4111.9558 | N23: =Model!N7/1000 -> 4329.8894 | O23: =Model!O7/1000 -> 4413.1565
B24: Cost of sales | C24: $M | G24: =(Model!G17-Model!G7)/1000 -> -557.424 | H24: =(Model!H17-Model!H7)/1000 -> -577.525 | I24: =(Model!I17-Model!I7)/1000 -> -830.025 | J24: =(Model!J17-Model!J7)/1000 -> -1299.167 | K24: =(Model!K17-Model!K7)/1000 -> -1553.3495 | L24: =(Model!L17-Model!L7)/1000 -> -1709.2402 | M24: =(Model!M17-Model!M7)/1000 -> -1853.7763 | N24: =(Model!N17-Model!N7)/1000 -> -1973.5794 | O24: =(Model!O17-Model!O7)/1000 -> -2053.5721
B25: Gross Profit | C25: $M | G25: =Model!G17/1000 -> 630.236 | H25: =Model!H17/1000 -> 591.249 | I25: =Model!I17/1000 -> 817.743 | J25: =Model!J17/1000 -> 1175.03 | K25: =Model!K17/1000 -> 1992.8786 | L25: =Model!L17/1000 -> 2122.3549 | M25: =Model!M17/1000 -> 2258.1795 | N25: =Model!N17/1000 -> 2356.31 | O25: =Model!O17/1000 -> 2359.5845
B26: Gross Margin | C26: % | G26: =IFERROR(Model!G17/Model!G7,"") -> 0.53065355 | H26: =IFERROR(Model!H17/Model!H7,"") -> 0.50587111 | I26: =IFERROR(Model!I17/Model!I7,"") -> 0.49627314 | J26: =IFERROR(Model!J17/Model!J7,"") -> 0.47491368 | K26: =IFERROR(Model!K17/Model!K7,"") -> 0.56197136 | L26: =IFERROR(Model!L17/Model!L7,"") -> 0.55390897 | M26: =IFERROR(Model!M17/Model!M7,"") -> 0.54917407 | N26: =IFERROR(Model!N17/Model!N7,"") -> 0.54419635 | O26: =IFERROR(Model!O17/Model!O7,"") -> 0.53467047
B27: Adjusted EBITDA | C27: $M | G27: =Model!G26/1000 -> 740.632 | H27: =Model!H26/1000 -> 755.927 | I27: =Model!I26/1000 -> 1039.586 | J27: =Model!J26/1000 -> 1576.59 | K27: =Model!K26/1000 -> 2316.8758 | L27: =Model!L26/1000 -> 2505.9558 | M27: =Model!M26/1000 -> 2695.3381 | N27: =Model!N26/1000 -> 2844.8547 | O27: =Model!O26/1000 -> 2903.5392
B28: EBITDA Margin | C28: % | G28: =IFERROR(Model!G26/Model!G7,"") -> 0.62360608 | H28: =IFERROR(Model!H26/Model!H7,"") -> 0.64676918 | I28: =IFERROR(Model!I26/Model!I7,"") -> 0.63090556 | J28: =IFERROR(Model!J26/Model!J7,"") -> 0.6372128 | K28: =IFERROR(Model!K26/Model!K7,"") -> 0.65333525 | L28: =IFERROR(Model!L26/Model!L7,"") -> 0.65402416 | M28: =IFERROR(Model!M26/Model!M7,"") -> 0.6554881 | N28: =IFERROR(Model!N26/Model!N7,"") -> 0.6570271 | O28: =IFERROR(Model!O26/Model!O7,"") -> 0.65792799
B29: D&A | C29: $M | G29: =Model!G14/1000 -> -234.862 | H29: =Model!H14/1000 -> -276.43 | I29: =Model!I14/1000 -> -437.699 | J29: =Model!J14/1000 -> -738.903 | K29: =Model!K14/1000 -> -848.26543 | L29: =Model!L14/1000 -> -950.05728 | M29: =Model!M14/1000 -> -1045.063 | N29: =Model!N14/1000 -> -1128.668 | O29: =Model!O14/1000 -> -1196.3881
B30: EBIT | C30: $M | G30: =Model!G27/1000 -> 529.147 | H30: =Model!H27/1000 -> 631.487 | I30: =Model!I27/1000 -> 625.39 | J30: =Model!J27/1000 -> 1250.83 | K30: =Model!K27/1000 -> 1468.6104 | L30: =Model!L27/1000 -> 1555.8985 | M30: =Model!M27/1000 -> 1650.2751 | N30: =Model!N27/1000 -> 1716.1867 | O30: =Model!O27/1000 -> 1707.1511
B31: EBIT Margin | C31: % | G31: =IFERROR(Model!G27/Model!G7,"") -> 0.44553744 | H31: =IFERROR(Model!H27/Model!H7,"") -> 0.54029864 | I31: =IFERROR(Model!I27/Model!I7,"") -> 0.37953765 | J31: =IFERROR(Model!J27/Model!J7,"") -> 0.50554988 | K31: =IFERROR(Model!K27/Model!K7,"") -> 0.41413309 | L31: =IFERROR(Model!L27/Model!L7,"") -> 0.4060707 | M31: =IFERROR(Model!M27/Model!M7,"") -> 0.4013358 | N31: =IFERROR(Model!N27/Model!N7,"") -> 0.39635808 | O31: =IFERROR(Model!O27/Model!O7,"") -> 0.3868322
B32: Net Income | C32: $M | G32: =Model!G42/1000 -> 269.535 | H32: =Model!H42/1000 -> 396.955 | I32: =Model!I42/1000 -> 477.521 | J32: =Model!J42/1000 -> 719.063 | K32: =Model!K42/1000 -> 873.74469 | L32: =Model!L42/1000 -> 948.48009 | M32: =Model!M42/1000 -> 1033.6708 | N32: =Model!N42/1000 -> 1104.8249 | O32: =Model!O42/1000 -> 1128.9243
B33: Net Income Margin | C33: % | G33: =IFERROR(Model!G42/Model!G7,"") -> 0.22694626 | H33: =IFERROR(Model!H42/Model!H7,"") -> 0.33963367 | I33: =IFERROR(Model!I42/Model!I7,"") -> 0.28979869 | J33: =IFERROR(Model!J42/Model!J7,"") -> 0.2906248 | K33: =IFERROR(Model!K42/Model!K7,"") -> 0.24638705 | L33: =IFERROR(Model!L42/Model!L7,"") -> 0.24754183 | M33: =IFERROR(Model!M42/Model!M7,"") -> 0.25138179 | N33: =IFERROR(Model!N42/Model!N7,"") -> 0.25516238 | O33: =IFERROR(Model!O42/Model!O7,"") -> 0.25580881
B34: EPS diluted | C34: $/share | G34: =Model!G47 -> 2.755 | H34: =Model!H47 -> 4 | I34: =Model!I47 -> 4.633 | J34: =Model!J47 -> 6.707 | K34: =Model!K47 -> 8.1497805 | L34: =Model!L47 -> 8.8468687 | M34: =Model!M47 -> 9.641478 | N34: =Model!N47 -> 10.305162 | O34: =Model!O47 -> 10.529947
B37: CASH FLOW STATEMENT
G39: 2022A | H39: 2023A | I39: 2024A | J39: 2025A | K39: 2026E | L39: 2027E | M39: 2028E | N39: 2029E | O39: 2030E
B41: Cash from Operations | C41: $M | G41: =Model!G130/1000 -> 689.771 | H41: =Model!H130/1000 -> 712.033 | I41: =Model!I130/1000 -> 959.026 | J41: =Model!J130/1000 -> 796.191 | K41: =Model!K130/1000 -> 1674.224 | L41: =Model!L130/1000 -> 1885.8171 | M41: =Model!M130/1000 -> 2066.2367 | N41: =Model!N130/1000 -> 2223.7785 | O41: =Model!O130/1000 -> 2321.6008
B42: Cash from Investing | C42: $M | G42: =Model!G136/1000 -> -582.712 | H42: =Model!H136/1000 -> -699.313 | I42: =Model!I136/1000 -> -1051.876 | J42: =Model!J136/1000 -> -2349.064 | K42: =Model!K136/1000 -> -1550 | L42: =Model!L136/1000 -> -1500 | M42: =Model!M136/1000 -> -1400 | N42: =Model!N136/1000 -> -1300 | O42: =Model!O136/1000 -> -1200
B43: of which CapEx | C43: $M | G43: =Model!G133/1000 -> -479.025 | H43: =Model!H133/1000 -> -688.437 | I43: =Model!I133/1000 -> -1052.53 | J43: =Model!J133/1000 -> -1455.411 | K43: =Model!K133/1000 -> -1550 | L43: =Model!L133/1000 -> -1500 | M43: =Model!M133/1000 -> -1400 | N43: =Model!N133/1000 -> -1300 | O43: =Model!O133/1000 -> -1200
B44: Cash from Financing | C44: $M | G44: =Model!G144/1000 -> -143.201 | H44: =Model!H144/1000 -> 19.556 | I44: =Model!I144/1000 -> 641.211 | J44: =Model!J144/1000 -> 1327.54 | K44: =Model!K144/1000 -> -350 | L44: =Model!L144/1000 -> -350 | M44: =Model!M144/1000 -> -350 | N44: =Model!N144/1000 -> -350 | O44: =Model!O144/1000 -> -350
B45: Change in Cash | C45: $M | G45: =Model!G146/1000 -> -36.142 | H45: =Model!H146/1000 -> 32.276 | I45: =Model!I146/1000 -> 548.361 | J45: =Model!J146/1000 -> -225.333 | K45: =Model!K146/1000 -> -225.77596 | L45: =Model!L146/1000 -> 35.817053 | M45: =Model!M146/1000 -> 316.23667 | N45: =Model!N146/1000 -> 573.7785 | O45: =Model!O146/1000 -> 771.60081
B46: Free Cash Flow (levered) | C46: $M | G46: =Model!G151/1000 -> 210.746 | H46: =Model!H151/1000 -> 23.596 | I46: =Model!I151/1000 -> -93.504 | J46: =Model!J151/1000 -> -659.22 | K46: =Model!K151/1000 -> 124.22404 | L46: =Model!L151/1000 -> 385.81705 | M46: =Model!M151/1000 -> 666.23667 | N46: =Model!N151/1000 -> 923.7785 | O46: =Model!O151/1000 -> 1121.6008
B47: FCF Margin | C47: % | G47: =IFERROR(Model!G151/Model!G7,"") -> 0.17744641 | H47: =IFERROR(Model!H151/Model!H7,"") -> 0.020188676 | I47: =IFERROR(Model!I151/Model!I7,"") -> -0.056745853 | J47: =IFERROR(Model!J151/Model!J7,"") -> -0.26643796 | K47: =IFERROR(Model!K151/Model!K7,"") -> 0.035029907 | L47: =IFERROR(Model!L151/Model!L7,"") -> 0.10069358 | M47: =IFERROR(Model!M151/Model!M7,"") -> 0.16202428 | N47: =IFERROR(Model!N151/Model!N7,"") -> 0.21334921 | O47: =IFERROR(Model!O151/Model!O7,"") -> 0.25414934
B50: BALANCE SHEET SUMMARY
G52: 2022A | H52: 2023A | I52: 2024A | J52: 2025A | K52: 2026E | L52: 2027E | M52: 2028E | N52: 2029E | O52: 2030E
B54: Cash & equivalents | C54: $M | G54: =Model!G72/1000 -> 244.385 | H54: =Model!H72/1000 -> 213.253 | I54: =Model!I72/1000 -> 764.307 | J54: =Model!J72/1000 -> 538.402 | K54: =Model!K72/1000 -> 312.62604 | L54: =Model!L72/1000 -> 348.44309 | M54: =Model!M72/1000 -> 664.67976 | N54: =Model!N72/1000 -> 1238.4583 | O54: =Model!O72/1000 -> 2010.0591
B55: Total assets | C55: $M | G55: =Model!G75/1000 -> 2037.979 | H55: =Model!H75/1000 -> 2598.003 | I55: =Model!I75/1000 -> 4232.372 | J55: =Model!J75/1000 -> 7112.853 | K55: =Model!K75/1000 -> 7905.1803 | L55: =Model!L75/1000 -> 8575.1552 | M55: =Model!M75/1000 -> 9329.0665 | N55: =Model!N75/1000 -> 10138.492 | O55: =Model!O75/1000 -> 10938.277
B56: Net debt | C56: $M | G56: =(Model!G96+Model!G107-Model!G72)/1000 -> 304.947 | H56: =(Model!H96+Model!H107-Model!H72)/1000 -> 402.802 | I56: =(Model!I96+Model!I107-Model!I72)/1000 -> 684.26 | J56: =(Model!J96+Model!J107-Model!J72)/1000 -> 2615.675 | K56: =(Model!K96+Model!K107-Model!K72)/1000 -> 2491.451 | L56: =(Model!L96+Model!L107-Model!L72)/1000 -> 2105.6339 | M56: =(Model!M96+Model!M107-Model!M72)/1000 -> 1439.3972 | N56: =(Model!N96+Model!N107-Model!N72)/1000 -> 515.61873 | O56: =(Model!O96+Model!O107-Model!O72)/1000 -> -605.98207
B57: Total equity | C57: $M | G57: =Model!G88/1000 -> 844.06 | H57: =Model!H88/1000 -> 1247.015 | I57: =Model!I88/1000 -> 1621.213 | J57: =Model!J88/1000 -> 2511.594 | K57: =Model!K88/1000 -> 3385.3387 | L57: =Model!L88/1000 -> 4333.8188 | M57: =Model!M88/1000 -> 5367.4896 | N57: =Model!N88/1000 -> 6472.3145 | O57: =Model!O88/1000 -> 7601.2388
B58: Net Debt / EBITDA | C58: x | G58: =IFERROR((Model!G96+Model!G107-Model!G72)/Model!G26,"") -> 0.41173889 | H58: =IFERROR((Model!H96+Model!H107-Model!H72)/Model!H26,"") -> 0.53285833 | I58: =IFERROR((Model!I96+Model!I107-Model!I72)/Model!I26,"") -> 0.65820432 | J58: =IFERROR((Model!J96+Model!J107-Model!J72)/Model!J26,"") -> 1.6590712 | K58: =IFERROR((Model!K96+Model!K107-Model!K72)/Model!K26,"") -> 1.0753494 | L58: =IFERROR((Model!L96+Model!L107-Model!L72)/Model!L26,"") -> 0.8402518 | M58: =IFERROR((Model!M96+Model!M107-Model!M72)/Model!M26,"") -> 0.53403217 | N58: =IFERROR((Model!N96+Model!N107-Model!N72)/Model!N26,"") -> 0.18124607 | O58: =IFERROR((Model!O96+Model!O107-Model!O72)/Model!O26,"") -> -0.20870463
B59: Interest coverage | C59: x | G59: =IFERROR(Model!G27/-Model!G31,"") -> 18.318459 | H59: =IFERROR(Model!H27/-Model!H31,"") -> 28.862699 | I59: =IFERROR(Model!I27/-Model!I31,"") -> 10.0064 | J59: =IFERROR(Model!J27/-Model!J31,"") -> 7.6570802 | K59: =IFERROR(Model!K27/-Model!K31,"") -> 6.208305 | L59: =IFERROR(Model!L27/-Model!L31,"") -> 7.3982683 | M59: =IFERROR(Model!M27/-Model!M31,"") -> 8.9661684 | N59: =IFERROR(Model!N27/-Model!N31,"") -> 10.87531 | O59: =IFERROR(Model!O27/-Model!O31,"") -> 12.976633
B60: ROACE | C60: % | G60: =IFERROR(Model!G27*(1+Model!G40/Model!G36)/(Model!G88+Model!G96+Model!G107-Model!G72),"") -> 0.28632924 | H60: =IFERROR(Model!H27*(1+Model!H40/Model!H36)/(Model!H88+Model!H96+Model!H107-Model!H72),"") -> 0.27860405 | I60: =IFERROR(Model!I27*(1+Model!I40/Model!I36)/(Model!I88+Model!I96+Model!I107-Model!I72),"") -> 0.21924164 | J60: =IFERROR(Model!J27*(1+Model!J40/Model!J36)/(Model!J88+Model!J96+Model!J107-Model!J72),"") -> 0.17460443 | K60: =IFERROR(Model!K27*(1+Model!K40/Model!K36)/(Model!K88+Model!K96+Model!K107-Model!K72),"") -> 0.17493008 | L60: =IFERROR(Model!L27*(1+Model!L40/Model!L36)/(Model!L88+Model!L96+Model!L107-Model!L72),"") -> 0.16913378 | M60: =IFERROR(Model!M27*(1+Model!M40/Model!M36)/(Model!M88+Model!M96+Model!M107-Model!M72),"") -> 0.16970938 | N60: =IFERROR(Model!N27*(1+Model!N40/Model!N36)/(Model!N88+Model!N96+Model!N107-Model!N72),"") -> 0.17191502 | O60: =IFERROR(Model!O27*(1+Model!O40/Model!O36)/(Model!O88+Model!O96+Model!O107-Model!O72),"") -> 0.17083086
B63: VALUATION SUMMARY
G65: 2022A | H65: 2023A | I65: 2024A | J65: 2025A | K65: 2026E | L65: 2027E | M65: 2028E | N65: 2029E | O65: 2030E
B67: Share price (current) | C67: $/share | K67: 64.64
B68: Shares outstanding | C68: M | K68: =Model!J42/Model!J47/1000 -> 107.21082
B69: Market cap | C69: $M | K69: =K67*K68 -> 6930.1077
B70: Net debt | C70: $M | K70: =J56 -> 2615.675
B71: Enterprise Value | C71: $M | K71: =K69+K70 -> 9545.7827
B73: EV/EBITDA (2026E) | C73: x | K73: =IFERROR(K71/K27,"") -> 4.1201097
B74: EV/BOE/día (2026E) | C74: $/boe/d | K74: =IFERROR(K71*1000000/K7,"") -> 71880.434
B76: DCF price target | C76: $/share | K76: =G110 -> 64.835751
B77: Comps price target | C77: $/share | K77: =IFERROR((K96*K27-K70)/K68,"") -> 83.654838
B78: Blended price target | C78: $/share | K78: =AVERAGE(K76,K77) -> 74.245295
B79: Upside / Downside | C79: % | K79: =IFERROR(K78/K67-1,"") -> 0.14859677
B82: SENSITIVITY ANALYSIS
B85: =K76 -> 64.835751 | C85: 0.11 | D85: 0.12 | E85: 0.13 | F85: 0.14 | G85: 0.15
B86: 70 | C86: =(C$118+($B86/$C$116-1)*$C$114*(1-$C$115)*C$119+(Model!$O$26/1000+Model!$O$7/1000*($B86/$C$116-1)*$C$114)*$G$96*C$120-$G$107)/$G$109 -> 41.137672 | D86: =(D$118+($B86/$C$116-1)*$C$114*(1-$C$115)*D$119+(Model!$O$26/1000+Model!$O$7/1000*($B86/$C$116-1)*$C$114)*$G$96*D$120-$G$107)/$G$109 -> 38.329593 | E86: =(E$118+($B86/$C$116-1)*$C$114*(1-$C$115)*E$119+(Model!$O$26/1000+Model!$O$7/1000*($B86/$C$116-1)*$C$114)*$G$96*E$120-$G$107)/$G$109 -> 35.66572 | F86: =(F$118+($B86/$C$116-1)*$C$114*(1-$C$115)*F$119+(Model!$O$26/1000+Model!$O$7/1000*($B86/$C$116-1)*$C$114)*$G$96*F$120-$G$107)/$G$109 -> 33.13744 | G86: =(G$118+($B86/$C$116-1)*$C$114*(1-$C$115)*G$119+(Model!$O$26/1000+Model!$O$7/1000*($B86/$C$116-1)*$C$114)*$G$96*G$120-$G$107)/$G$109 -> 30.736728
B87: 75 | C87: =(C$118+($B87/$C$116-1)*$C$114*(1-$C$115)*C$119+(Model!$O$26/1000+Model!$O$7/1000*($B87/$C$116-1)*$C$114)*$G$96*C$120-$G$107)/$G$109 -> 51.581387 | D87: =(D$118+($B87/$C$116-1)*$C$114*(1-$C$115)*D$119+(Model!$O$26/1000+Model!$O$7/1000*($B87/$C$116-1)*$C$114)*$G$96*D$120-$G$107)/$G$109 -> 48.40426 | E87: =(E$118+($B87/$C$116-1)*$C$114*(1-$C$115)*E$119+(Model!$O$26/1000+Model!$O$7/1000*($B87/$C$116-1)*$C$114)*$G$96*E$120-$G$107)/$G$109 -> 45.389064 | F87: =(F$118+($B87/$C$116-1)*$C$114*(1-$C$115)*F$119+(Model!$O$26/1000+Model!$O$7/1000*($B87/$C$116-1)*$C$114)*$G$96*F$120-$G$107)/$G$109 -> 42.526161 | G87: =(G$118+($B87/$C$116-1)*$C$114*(1-$C$115)*G$119+(Model!$O$26/1000+Model!$O$7/1000*($B87/$C$116-1)*$C$114)*$G$96*G$120-$G$107)/$G$109 -> 39.806571
B88: 80 | C88: =(C$118+($B88/$C$116-1)*$C$114*(1-$C$115)*C$119+(Model!$O$26/1000+Model!$O$7/1000*($B88/$C$116-1)*$C$114)*$G$96*C$120-$G$107)/$G$109 -> 62.025101 | D88: =(D$118+($B88/$C$116-1)*$C$114*(1-$C$115)*D$119+(Model!$O$26/1000+Model!$O$7/1000*($B88/$C$116-1)*$C$114)*$G$96*D$120-$G$107)/$G$109 -> 58.478927 | E88: =(E$118+($B88/$C$116-1)*$C$114*(1-$C$115)*E$119+(Model!$O$26/1000+Model!$O$7/1000*($B88/$C$116-1)*$C$114)*$G$96*E$120-$G$107)/$G$109 -> 55.112408 | F88: =(F$118+($B88/$C$116-1)*$C$114*(1-$C$115)*F$119+(Model!$O$26/1000+Model!$O$7/1000*($B88/$C$116-1)*$C$114)*$G$96*F$120-$G$107)/$G$109 -> 51.914882 | G88: =(G$118+($B88/$C$116-1)*$C$114*(1-$C$115)*G$119+(Model!$O$26/1000+Model!$O$7/1000*($B88/$C$116-1)*$C$114)*$G$96*G$120-$G$107)/$G$109 -> 48.876414
B89: 85 | C89: =(C$118+($B89/$C$116-1)*$C$114*(1-$C$115)*C$119+(Model!$O$26/1000+Model!$O$7/1000*($B89/$C$116-1)*$C$114)*$G$96*C$120-$G$107)/$G$109 -> 72.468815 | D89: =(D$118+($B89/$C$116-1)*$C$114*(1-$C$115)*D$119+(Model!$O$26/1000+Model!$O$7/1000*($B89/$C$116-1)*$C$114)*$G$96*D$120-$G$107)/$G$109 -> 68.553594 | E89: =(E$118+($B89/$C$116-1)*$C$114*(1-$C$115)*E$119+(Model!$O$26/1000+Model!$O$7/1000*($B89/$C$116-1)*$C$114)*$G$96*E$120-$G$107)/$G$109 -> 64.835751 | F89: =(F$118+($B89/$C$116-1)*$C$114*(1-$C$115)*F$119+(Model!$O$26/1000+Model!$O$7/1000*($B89/$C$116-1)*$C$114)*$G$96*F$120-$G$107)/$G$109 -> 61.303604 | G89: =(G$118+($B89/$C$116-1)*$C$114*(1-$C$115)*G$119+(Model!$O$26/1000+Model!$O$7/1000*($B89/$C$116-1)*$C$114)*$G$96*G$120-$G$107)/$G$109 -> 57.946257
B90: 90 | C90: =(C$118+($B90/$C$116-1)*$C$114*(1-$C$115)*C$119+(Model!$O$26/1000+Model!$O$7/1000*($B90/$C$116-1)*$C$114)*$G$96*C$120-$G$107)/$G$109 -> 82.91253 | D90: =(D$118+($B90/$C$116-1)*$C$114*(1-$C$115)*D$119+(Model!$O$26/1000+Model!$O$7/1000*($B90/$C$116-1)*$C$114)*$G$96*D$120-$G$107)/$G$109 -> 78.628262 | E90: =(E$118+($B90/$C$116-1)*$C$114*(1-$C$115)*E$119+(Model!$O$26/1000+Model!$O$7/1000*($B90/$C$116-1)*$C$114)*$G$96*E$120-$G$107)/$G$109 -> 74.559095 | F90: =(F$118+($B90/$C$116-1)*$C$114*(1-$C$115)*F$119+(Model!$O$26/1000+Model!$O$7/1000*($B90/$C$116-1)*$C$114)*$G$96*F$120-$G$107)/$G$109 -> 70.692325 | G90: =(G$118+($B90/$C$116-1)*$C$114*(1-$C$115)*G$119+(Model!$O$26/1000+Model!$O$7/1000*($B90/$C$116-1)*$C$114)*$G$96*G$120-$G$107)/$G$109 -> 67.0161
B91: 95 | C91: =(C$118+($B91/$C$116-1)*$C$114*(1-$C$115)*C$119+(Model!$O$26/1000+Model!$O$7/1000*($B91/$C$116-1)*$C$114)*$G$96*C$120-$G$107)/$G$109 -> 93.356244 | D91: =(D$118+($B91/$C$116-1)*$C$114*(1-$C$115)*D$119+(Model!$O$26/1000+Model!$O$7/1000*($B91/$C$116-1)*$C$114)*$G$96*D$120-$G$107)/$G$109 -> 88.702929 | E91: =(E$118+($B91/$C$116-1)*$C$114*(1-$C$115)*E$119+(Model!$O$26/1000+Model!$O$7/1000*($B91/$C$116-1)*$C$114)*$G$96*E$120-$G$107)/$G$109 -> 84.282439 | F91: =(F$118+($B91/$C$116-1)*$C$114*(1-$C$115)*F$119+(Model!$O$26/1000+Model!$O$7/1000*($B91/$C$116-1)*$C$114)*$G$96*F$120-$G$107)/$G$109 -> 80.081046 | G91: =(G$118+($B91/$C$116-1)*$C$114*(1-$C$115)*G$119+(Model!$O$26/1000+Model!$O$7/1000*($B91/$C$116-1)*$C$114)*$G$96*G$120-$G$107)/$G$109 -> 76.085943
B92: 100 | C92: =(C$118+($B92/$C$116-1)*$C$114*(1-$C$115)*C$119+(Model!$O$26/1000+Model!$O$7/1000*($B92/$C$116-1)*$C$114)*$G$96*C$120-$G$107)/$G$109 -> 103.79996 | D92: =(D$118+($B92/$C$116-1)*$C$114*(1-$C$115)*D$119+(Model!$O$26/1000+Model!$O$7/1000*($B92/$C$116-1)*$C$114)*$G$96*D$120-$G$107)/$G$109 -> 98.777596 | E92: =(E$118+($B92/$C$116-1)*$C$114*(1-$C$115)*E$119+(Model!$O$26/1000+Model!$O$7/1000*($B92/$C$116-1)*$C$114)*$G$96*E$120-$G$107)/$G$109 -> 94.005783 | F92: =(F$118+($B92/$C$116-1)*$C$114*(1-$C$115)*F$119+(Model!$O$26/1000+Model!$O$7/1000*($B92/$C$116-1)*$C$114)*$G$96*F$120-$G$107)/$G$109 -> 89.469767 | G92: =(G$118+($B92/$C$116-1)*$C$114*(1-$C$115)*G$119+(Model!$O$26/1000+Model!$O$7/1000*($B92/$C$116-1)*$C$114)*$G$96*G$120-$G$107)/$G$109 -> 85.155786
B95: DCF CALCULATION
B96: WACC | C96: 0.13 | E96: Exit multiple (EV/EBITDA) | G96: 4.5 | I96: Comps EV/EBITDA mult | K96: 5
G98: 2026E | H98: 2027E | I98: 2028E | J98: 2029E | K98: 2030E
B99: Unlevered Free Cash Flow ($M) | G99: =Model!K152/1000 -> 278.50664 | H99: =Model!L152/1000 -> 526.46595 | I99: =Model!M152/1000 -> 787.75841 | J99: =Model!N152/1000 -> 1020.2843 | K99: =Model!O152/1000 -> 1187.6822
B100: Discount period | G100: 1 | H100: 2 | I100: 3 | J100: 4 | K100: 5
B101: Discount factor | G101: =1/(1+$C$96)^G100 -> 0.88495575 | H101: =1/(1+$C$96)^H100 -> 0.78314668 | I101: =1/(1+$C$96)^I100 -> 0.69305016 | J101: =1/(1+$C$96)^J100 -> 0.61331873 | K101: =1/(1+$C$96)^K100 -> 0.54275994
B102: PV of Free Cash Flow ($M) | G102: =G99*G101 -> 246.46605 | H102: =H99*H101 -> 412.30006 | I102: =I99*I101 -> 545.95609 | J102: =J99*J101 -> 625.75945 | K102: =K99*K101 -> 644.62633
B103: Sum PV of FCF ($M) | G103: =SUM(G102:K102) -> 2475.108
B104: Terminal value (EBITDA 2030E × mult) ($M) | G104: =Model!O26/1000*$G$96 -> 13065.926
B105: PV of terminal value ($M) | G105: =G104*K101 -> 7091.6614
B106: Enterprise Value ($M) | G106: =G103+G105 -> 9566.7694
B107: Less: Net debt (2025A) ($M) | G107: =J56 -> 2615.675
B108: Equity Value ($M) | G108: =G106-G107 -> 6951.0944
B109: Shares outstanding (M) | G109: =K68 -> 107.21082
B110: DCF value per share ($) | G110: =G108/G109 -> 64.835751
B113: SENSITIVITY ENGINE (Brent × WACC)
B114: Incremental EBITDA margin on Brent revenue | C114: 0.86
B115: Tax rate | C115: ='Imputs Drivers'!G38 -> 0.3
B116: Brent reference ($/bbl, = active 2026E) | C116: ='Imputs Drivers'!G8 -> 85
B118: PV of base FCF ($M) | C118: {=SUMPRODUCT($G$99:$K$99,1/(1+C$85)^$G$100:$K$100)} -> 2631.1251 | D118: {=SUMPRODUCT($G$99:$K$99,1/(1+D$85)^$G$100:$K$100)} -> 2551.4048 | E118: {=SUMPRODUCT($G$99:$K$99,1/(1+E$85)^$G$100:$K$100)} -> 2475.108 | F118: {=SUMPRODUCT($G$99:$K$99,1/(1+F$85)^$G$100:$K$100)} -> 2402.0521 | G118: {=SUMPRODUCT($G$99:$K$99,1/(1+G$85)^$G$100:$K$100)} -> 2332.0663
B119: PV of base Revenue ($M) | C119: {=SUMPRODUCT(Model!$K$7:$O$7/1000,1/(1+C$85)^$G$100:$K$100)} -> 14782.461 | D119: {=SUMPRODUCT(Model!$K$7:$O$7/1000,1/(1+D$85)^$G$100:$K$100)} -> 14403.475 | E119: {=SUMPRODUCT(Model!$K$7:$O$7/1000,1/(1+E$85)^$G$100:$K$100)} -> 14039.634 | F119: {=SUMPRODUCT(Model!$K$7:$O$7/1000,1/(1+F$85)^$G$100:$K$100)} -> 13690.165 | G119: {=SUMPRODUCT(Model!$K$7:$O$7/1000,1/(1+G$85)^$G$100:$K$100)} -> 13354.338
B120: Discount factor year 5 | C120: =1/(1+C$85)^5 -> 0.59345133 | D120: =1/(1+D$85)^5 -> 0.56742686 | E120: =1/(1+E$85)^5 -> 0.54275994 | F120: =1/(1+F$85)^5 -> 0.51936866 | G120: =1/(1+G$85)^5 -> 0.49717674

Sheet Imput Historical
B3: INCOME STATEMENT (P&L)
B5: Amounts expressed in thousands of US Dollars | G5: 2022 | H5: 2023 | I5: 2024 | J5: 2025
B7: Revenue from contracts with customers | G7: 1187660 | H7: 1168774 | I7: 1647768 | J7: 2474197
B9: Cost of sales
B11: Operating costs | G11: -133385 | H11: -94685 | I11: -116526 | J11: -186945
B12: Crude oil stock fluctuation | G12: -500 | H12: -2058 | I12: 1720 | J12: 1046
B13: Royalties and others | G13: -188677 | H13: -176813 | I13: -243950 | J13: -345349
B14: Depreciation, depletion and amortization | G14: -234862 | H14: -276430 | I14: -437699 | J14: -738903
B15: Other non-cash costs | G15: 0 | H15: -27539 | I15: -33570 | J15: -29016
B17: Gross profit | G17: 630236 | H17: 591249 | I17: 817743 | J17: 1175030
B19: Selling expenses | G19: -59904 | H19: -68792 | I19: -140334 | J19: -218072
B20: General and administrative expenses | G20: -63826 | H20: -70483 | I20: -108954 | J20: -147709
B21: Exploration expenses | G21: -736 | H21: -16 | I21: -138 | J21: -578
B22: Other operating income | G22: 26698 | H22: 203812 | I22: 54127 | J22: 512793
B23: Other operating expenses | G23: -3321 | H23: 302 | I23: -1261 | J23: -32382
B24: Impairment of long-lived assets | G24: 0 | H24: -24585 | I24: 4207 | J24: -38252
... B41: Profit for the year, net | G41: 269535 | H41: 396955 | I41: 477521 | J41: 719063
B43: Other comprehensive income
B45: Actuarial remeasurement | G45: -4181 | H45: 6565 | I45: -10200 | J45: 36
B46: Deferred income tax on OCI | G46: 1463 | H46: -2298 | I46: 3570 | J46: -13
B48: Other comprehensive income for the year | G48: -2718 | H48: 4267 | I48: -6630 | J48: 23
B50: Total comprehensive profit for the year | G50: 266817 | H50: 401222 | I50: 470891 | J50: 719086
B52: Earnings per share
B54: Basic (USD per share) | G54: 3.068 | H54: 4.237 | I54: 4.979 | J54: 7.015
B55: Diluted (USD per share) | G55: 2.755 | H55: 4 | I55: 4.633 | J55: 6.707
B58: CASH FLOW STATEMENT
B60: Amounts expressed in thousands of US Dollars | G60: 2022 | H60: 2023 | I60: 2024 | J60: 2025
B62: Cash flows from operating activities:
B63: Profit for the year, net | G63: 269535 | H63: 396955 | I63: 477521 | J63: 719063
B65: Adjustments to reconcile net cash flows
B66: Items related to operating activities:
B67: Allowance for expected credit losses | G67: -36 | H67: 0 | I67: 0 | J67: 44
B68: Share-based payments | G68: 16576 | H68: 23133 | I68: 34923 | J68: 55989
B69: Net increase in provisions | G69: 2790 | H69: -578 | I69: 1261 | J69: 2507
B70: Net changes in foreign exchange rate | G70: -33263 | H70: -18458 | I70: 453 | J70: 144
B71: Discount of assets and liabilities at present value | G71: 2561 | H71: -2137 | I71: -933 | J71: 23652
B72: Discount for well plugging and abandonment | G72: 2444 | H72: 2387 | I72: 1312 | J72: 2434
B73: Income tax expense | G73: 163979 | H73: 148404 | I73: 113306 | J73: 285608
B74: Other non-cash costs related to the transfer of conventional assets | G74: 0 | H74: 27539 | I74: 33570 | J74: 29016
B75: Employee benefits | G75: 502 | H75: 300 | I75: 489 | J75: 788
B77: Items related to investing activities:
B78: Impairment of long-lived assets | G78: 0 | H78: 24585 | I78: -4207 | J78: 38252
B79: Gain from Business Combination | G79: 0 | H79: 0 | I79: 0 | J79: -490530
B80: Interest income | G80: -809 | H80: -1235 | I80: -4535 | J80: -10594
B81: Changes in the fair value of financial assets | G81: 17599 | H81: -19437 | I81: -14120 | J81: -18471
B82: Depreciation and depletion | G82: 231746 | H82: 272371 | I82: 431788 | J82: 730248
B83: Amortization of intangible assets | G83: 3116 | H83: 4059 | I83: 5911 | J83: 8655
B84: Income (loss) from investment in associates | G84: 0 | H84: 0 | I84: 0 | J84: 5214
B85: Gain related to the transfer of conventional assets | G85: 0 | H85: -89659 | I85: 0 | J85: 0
B86: Gain from farmout agreement | G86: -18218 | H86: -24429 | I86: 0 | J86: 0
B88: Items related to financing activities:
B89: Interest expense | G89: 28886 | H89: 21879 | I89: 62499 | J89: 163356
B90: Amortized cost | G90: 2365 | H90: 1810 | I90: 1649 | J90: 7880
B91: Interest expense on lease liabilities | G91: 1925 | H91: 2894 | I91: 3093 | J91: 3320
B92: Other taxes interest | G92: 30350 | H92: 0 | I92: 0 | J92: 55101
B93: Other financial income (expense) | G93: -9242 | H93: 26381 | I93: -14855 | J93: 14123
B94: Remeasurement in borrowings | G94: 52817 | H94: 72044 | I94: 0 | J94: 0
B96: Changes in working capital:
B97: Trade and other receivables | G97: -34515 | H97: -81260 | I97: -210622 | J97: -221134
B98: Inventories | G98: 500 | H98: 2058 | I98: -1720 | J98: -1046
B99: Trade and other payables | G99: 40183 | H99: 61230 | I99: 112380 | J99: -39172
B100: Payments of employee benefits | G100: -254 | H100: -283 | I100: -424 | J100: -494
B101: Salaries and payroll taxes | G101: 2877 | H101: -26441 | I101: -16247 | J101: -109852
B102: Other taxes and royalties | G102: -8024 | H102: -43507 | I102: -23396 | J102: -24660
B103: Provisions | G103: -2265 | H103: -1359 | I103: -751 | J103: -1600
B104: Income tax payment | G104: -74354 | H104: -67213 | I104: -29319 | J104: -431650
B106: Net cash flows provided by operating activities | G106: 689771 | H106: 712033 | I106: 959026 | J106: 796191
B108: Cash flows from investing activities:
B109: Payments for acquisitions of property, plant and equipment and biological assets | G109: -479025 | H109: -688437 | I109: -1052530 | J109: -1455411
B110: Interest received | G110: 809 | H110: 1235 | I110: 4535 | J110: 10594
B111: Payments for acquisitions of other intangible assets | G111: -6030 | H111: -7293 | I111: -11328 | J111: -11720
B112: Proceeds from the transfer of conventional assets | G112: 0 | H112: 10000 | I112: 10734 | J112: 5734
B113: Payments for investments in associates | G113: -3466 | H113: -2176 | I113: -3287 | J113: -56706
B114: Payment for Business Combination, net of cash acquired | G114: 0 | H114: 0 | I114: 0 | J114: -841555
B115: Proceeds from farmout agreement | G115: 20000 | H115: 26650 | I115: 0 | J115: 0
B116: Prepayment of leases | G116: 0 | H116: -14292 | I116: 0 | J116: 0
B117: Payments for the acquisition of AFBN assets | G117: -115000 | H117: -25000 | I117: 0 | J117: 0
B119: Net cash flows (used in) investing activities | G119: -582712 | H119: -699313 | I119: -1051876 | J119: -2349064
B121: Cash flows from financing activities:
B122: Proceeds from borrowings | G122: 128788 | H122: 318169 | I122: 1320897 | J122: 2838173
B123: Payment of borrowings principal | G123: -195091 | H123: -211499 | I123: -470351 | J123: -1173623
B124: Payment of borrowings interest | G124: -34430 | H124: -22993 | I124: -53897 | J124: -148310
B125: Payment of borrowings cost | G125: -1670 | H125: -1779 | I125: -7631 | J125: -17935
B126: Payments of other taxes interest | G126: 0 | H126: 0 | I126: 0 | J126: -22045
B127: Payments of other financial results | G127: 0 | H127: -25562 | I127: 8680 | J127: -7948
B128: Payment of lease | G128: -11494 | H128: -36780 | I128: -56641 | J128: -90772
B129: Share repurchase | G129: -29304 | H129: 0 | I129: -99846 | J129: -50000
B131: Net cash flows provided by financing activities | G131: -143201 | H131: 19556 | I131: 641211 | J131: 1327540
B133: Net (decrease) increase in cash and cash equivalents | G133: -36142 | H133: 32276 | I133: 548361 | J133: -225333
B134: Cash and cash equivalents at beginning of year | G134: 311217 | H134: 241956 | I134: 209516 | J134: 755610
B135: Effect of exposure to changes in the foreign currency rate and other financial results of cash and cash equivalents | G135: -33119 | H135: -64716 | I135: -2267 | J135: -4093
... B137: Cash and cash equivalents at end of year | G137: 241956 | H137: 209516 | I137: 755610 | J137: 526184
B139: Significant transactions that generated no cash flows
B140: Acquisition of Vista Lach through the issuance of Series A shares and an increase in trade and other payables | G140: 0 | H140: 0 | I140: 0 | J140: 506754
B141: Acquisition of property, plant and equipment through increase in trade and other payables | G141: 138543 | H141: 152607 | I141: 341448 | J141: 141181
B142: Acquisition of property, plant and equipment through increase in trade and other payables, related to the Farmout Agreement | G142: 0 | H142: 0 | I142: 0 | J142: 109538
B143: Changes in well plugging and abandonment with an impact in property, plant and equipment | G143: -713 | H143: -930 | I143: 23325 | J143: 5397
B144: Disposal for transfer of conventional assets through increase in trade and other receivables | G144: 0 | H144: -116071 | I144: 0 | J144: 0
B147: BALANCE SHEET
B149: Amounts expressed in thousands of US Dollars | G149: 2022 | H149: 2023 | I149: 2024 | J149: 2025
...

Sheet Imputs Drivers
B3: DRIVERS
B5: Driver Switch | C5: Base Case | G5: 2026E | H5: 2027E | I5: 2028E | J5: 2029E | K5: 2030E
B8: Brent Price ($/bbl) | G8: =INDEX(G10:G12,MATCH($C$5,$B$10:$B$12,0)) -> 85 | H8: =INDEX(H10:H12,MATCH($C$5,$B$10:$B$12,0)) -> 82 | I8: =INDEX(I10:I12,MATCH($C$5,$B$10:$B$12,0)) -> 80 | J8: =INDEX(J10:J12,MATCH($C$5,$B$10:$B$12,0)) -> 78 | K8: =INDEX(K10:K12,MATCH($C$5,$B$10:$B$12,0)) -> 75
B10: Best Case | G10: 95 | H10: 92 | I10: 90 | J10: 88 | K10: 85
B11: Base Case | G11: 85 | H11: 82 | I11: 80 | J11: 78 | K11: 75
B12: Worst Case | G12: 61.5 | H12: 64 | I12: 65.3 | J12: 63.4 | K12: 63.4
B14: Production Growth (% YoY) | G14: =INDEX(G16:G18,MATCH($C$5,$B$10:$B$12,0)) -> 0.15 | H14: =INDEX(H16:H18,MATCH($C$5,$B$10:$B$12,0)) -> 0.12 | I14: =INDEX(I16:I18,MATCH($C$5,$B$10:$B$12,0)) -> 0.1 | J14: =INDEX(J16:J18,MATCH($C$5,$B$10:$B$12,0)) -> 0.08 | K14: =INDEX(K16:K18,MATCH($C$5,$B$10:$B$12,0)) -> 0.06
B16: =$B$10 -> Best Case | G16: 0.25 | H16: 0.2 | I16: 0.15 | J16: 0.12 | K16: 0.1
B17: =$B$11 -> Base Case | G17: 0.15 | H17: 0.12 | I17: 0.1 | J17: 0.08 | K17: 0.06
B18: =$B$12 -> Worst Case | G18: 0.05 | H18: 0.05 | I18: 0.04 | J18: 0.04 | K18: 0.03
B20: Lifting Cost ($/boe) | G20: =INDEX(G22:G24,MATCH($C$5,$B$10:$B$12,0)) -> 4.3 | H20: =INDEX(H22:H24,MATCH($C$5,$B$10:$B$12,0)) -> 4.1 | I20: =INDEX(I22:I24,MATCH($C$5,$B$10:$B$12,0)) -> 3.9 | J20: =INDEX(J22:J24,MATCH($C$5,$B$10:$B$12,0)) -> 3.7 | K20: =INDEX(K22:K24,MATCH($C$5,$B$10:$B$12,0)) -> 3.5
B22: =$B$10 -> Best Case | G22: 3.8 | H22: 3.6 | I22: 3.4 | J22: 3.2 | K22: 3
B23: =$B$11 -> Base Case | G23: 4.3 | H23: 4.1 | I23: 3.9 | J23: 3.7 | K23: 3.5
B24: =$B$12 -> Worst Case | G24: 5 | H24: 4.8 | I24: 4.6 | J24: 4.4 | K24: 4.2
B26: CapEx ($M) | G26: =INDEX(G28:G30,MATCH($C$5,$B$10:$B$12,0)) -> 1550 | H26: =INDEX(H28:H30,MATCH($C$5,$B$10:$B$12,0)) -> 1500 | I26: =INDEX(I28:I30,MATCH($C$5,$B$10:$B$12,0)) -> 1400 | J26: =INDEX(J28:J30,MATCH($C$5,$B$10:$B$12,0)) -> 1300 | K26: =INDEX(K28:K30,MATCH($C$5,$B$10:$B$12,0)) -> 1200
B28: =$B$10 -> Best Case | G28: 1400 | H28: 1300 | I28: 1200 | J28: 1100 | K28: 1000
B29: =$B$11 -> Base Case | G29: 1550 | H29: 1500 | I29: 1400 | J29: 1300 | K29: 1200
B30: =$B$12 -> Worst Case | G30: 1700 | H30: 1650 | I30: 1600 | J30: 1500 | K30: 1400
B33: FINANCIAL & TAX ASSUMPTIONS
B34: (applied to all scenarios) | G34: 2026E | H34: 2027E | I34: 2028E | J34: 2029E | K34: 2030E
B36: Interest rate on gross debt (%) | G36: 0.075 | H36: 0.075 | I36: 0.075 | J36: 0.075 | K36: 0.075
B37: Interest rate earned on cash (%) | G37: 0.03 | H37: 0.03 | I37: 0.03 | J37: 0.03 | K37: 0.03
B38: Effective tax rate (%) | G38: 0.3 | H38: 0.3 | I38: 0.3 | J38: 0.3 | K38: 0.3
B39: Debt repayment ($M) | G39: 350 | H39: 350 | I39: 350 | J39: 350 | K39: 350
B40: New borrowings ($M) | G40: 0 | H40: 0 | I40: 0 | J40: 0 | K40: 0
B41: Minimum cash balance ($M) | G41: 200 | H41: 200 | I41: 200 | J41: 200 | K41: 200
B42: DD&A rate ($/boe) | G42: 17.5 | H42: 17.5 | I42: 17.5 | J42: 17.5 | K42: 17.5
B43: Sources / basis for the assumptions above:
B44: Interest rate 7.5% ≈ implied 2025A rate (interest expense 163,356 / average gross debt 2,301,322 = 7.1%). Source: Imput Historical rows 30, 192, 203.
B45: Effective tax rate 30.0% vs. historical 37.8% / 27.2% / 19.2% / 28.4% (2022–2025 avg 28.2%); Argentine statutory rate is 35%. Source: Imput Historical rows 35, 39.
B46: Debt repayment $350M/yr = 2025A current portion of borrowings (350,095 k); new borrowings set to zero. Source: Imput Historical row 203.
B47: Minimum cash $200M: below this level the model draws on a revolver (Model rows 176–179); excess cash above it repays the revolver first.
B48: DD&A rate $17.5/boe = 2025A implied rate (historical: 13.3 / 14.8 / 17.2 / 17.5). Source: Imput Historical row 222. Depletion is now volume-driven, not price-driven.

Sheet Model
B3: INCOME STATEMENT
B5: Amounts expressed in thousands of US Dollars | G5: 2022A | H5: 2023A | I5: 2024A | J5: 2025A | K5: 2026E | L5: 2027E | M5: 2028E | N5: 2029E | O5: 2030E
B7: Revenue from contracts with customers | G7: ='Imput Historical'!G7 -> 1187660 | H7: ='Imput Historical'!H7 -> 1168774 | I7: ='Imput Historical'!I7 -> 1647768 | J7: ='Imput Historical'!J7 -> 2474197 | K7: =J7*(1+'Imputs Drivers'!G14)*(K156/J156) -> 3546228.1 | L7: =K7*(1+'Imputs Drivers'!H14)*(L156/K156) -> 3831595.2 | M7: =L7*(1+'Imputs Drivers'!I14)*(M156/L156) -> 4111955.8 | N7: =M7*(1+'Imputs Drivers'!J14)*(N156/M156) -> 4329889.4 | O7: =N7*(1+'Imputs Drivers'!K14)*(O156/N156) -> 4413156.5
B9: Cost of sales
B11: Operating costs | G11: ='Imput Historical'!G11 -> -133385 | H11: ='Imput Historical'!H11 -> -94685 | I11: ='Imput Historical'!I11 -> -116526 | J11: ='Imput Historical'!J11 -> -186945 | K11: =J11*(1+'Imputs Drivers'!G14)*(K157/J157) -> -210100.69 | L11: =K11*(1+'Imputs Drivers'!H14)*(L157/K157) -> -224367.99 | M11: =L11*(1+'Imputs Drivers'!I14)*(M157/L157) -> -234765.53 | N11: =M11*(1+'Imputs Drivers'!J14)*(N157/M157) -> -240544.37 | O11: =N11*(1+'Imputs Drivers'!K14)*(O157/N157) -> -241194.49
B12: Crude oil stock fluctuation | G12: ='Imput Historical'!G12 -> -500 | H12: ='Imput Historical'!H12 -> -2058 | I12: ='Imput Historical'!I12 -> 1720 | J12: ='Imput Historical'!J12 -> 1046 | K12: 0 | L12: 0 | M12: 0 | N12: 0 | O12: 0
B13: Royalties and others | G13: ='Imput Historical'!G13 -> -188677 | H13: ='Imput Historical'!H13 -> -176813 | I13: ='Imput Historical'!I13 -> -243950 | J13: ='Imput Historical'!J13 -> -345349 | K13: =K7*($J$13/$J$7) -> -494983.35 | L13: =L7*($J$13/$J$7) -> -534814.96 | M13: =M7*($J$13/$J$7) -> -573947.76 | N13: =N7*($J$13/$J$7) -> -604366.99 | O13: =O7*($J$13/$J$7) -> -615989.43
B14: Depreciation, depletion and amortization | G14: ='Imput Historical'!G14 -> -234862 | H14: ='Imput Historical'!H14 -> -276430 | I14: ='Imput Historical'!I14 -> -437699 | J14: ='Imput Historical'!J14 -> -738903 | K14: =-K158*365*K159/1000 -> -848265.43 | L14: =-L158*365*L159/1000 -> -950057.28 | M14: =-M158*365*M159/1000 -> -1045063 | N14: =-N158*365*N159/1000 -> -1128668 | O14: =-O158*365*O159/1000 -> -1196388.1
B15: Other non-cash costs | G15: ='Imput Historical'!G15 -> 0 | H15: ='Imput Historical'!H15 -> -27539 | I15: ='Imput Historical'!I15 -> -33570 | J15: ='Imput Historical'!J15 -> -29016 | K15: 0 | L15: 0 | M15: 0 | N15: 0 | O15: 0
B17: Gross profit | G17: =G7+G11+G12+G13+G14+G15 -> 630236 | H17: =H7+H11+H12+H13+H14+H15 -> 591249 | I17: =I7+I11+I12+I13+I14+I15 -> 817743 | J17: =J7+J11+J12+J13+J14+J15 -> 1175030 | K17: =K7+K11+K12+K13+K14+K15 -> 1992878.6 | L17: =L7+L11+L12+L13+L14+L15 -> 2122354.9 | M17: =M7+M11+M12+M13+M14+M15 -> 2258179.5 | N17: =N7+N11+N12+N13+N14+N15 -> 2356310 | O17: =O7+O11+O12+O13+O14+O15 -> 2359584.5
B19: Selling expenses | G19: ='Imput Historical'!G19 -> -59904 | H19: ='Imput Historical'!H19 -> -68792 | I19: ='Imput Historical'!I19 -> -140334 | J19: ='Imput Historical'!J19 -> -218072 | K19: =K7*($J$19/$J$7) -> -312559.21 | L19: =L7*($J$19/$J$7) -> -337711.03 | M19: =M7*($J$19/$J$7) -> -362421.59 | N19: =N7*($J$19/$J$7) -> -381629.94 | O19: =O7*($J$19/$J$7) -> -388968.98
B20: General and administrative expenses | G20: ='Imput Historical'!G20 -> -63826 | H20: ='Imput Historical'!H20 -> -70483 | I20: ='Imput Historical'!I20 -> -108954 | J20: ='Imput Historical'!J20 -> -147709 | K20: =K7*($J$20/$J$7) -> -211709.01 | L20: =L7*($J$20/$J$7) -> -228745.36 | M20: =M7*($J$20/$J$7) -> -245482.83 | N20: =N7*($J$20/$J$7) -> -258493.42 | O20: =O7*($J$20/$J$7) -> -263464.45
B21: Exploration expenses | G21: ='Imput Historical'!G21 -> -736 | H21: ='Imput Historical'!H21 -> -16 | I21: ='Imput Historical'!I21 -> -138 | J21: ='Imput Historical'!J21 -> -578 | K21: 0 | L21: 0 | M21: 0 | N21: 0 | O21: 0
B22: Other operating income | G22: ='Imput Historical'!G22 -> 26698 | H22: ='Imput Historical'!H22 -> 203812 | I22: ='Imput Historical'!I22 -> 54127 | J22: ='Imput Historical'!J22 -> 512793 | K22: 0 | L22: 0 | M22: 0 | N22: 0 | O22: 0
B23: Other operating expenses | G23: ='Imput Historical'!G23 -> -3321 | H23: ='Imput Historical'!H23 -> 302 | I23: ='Imput Historical'!I23 -> -1261 | J23: ='Imput Historical'!J23 -> -32382 | K23: 0 | L23: 0 | M23: 0 | N23: 0 | O23: 0
B24: Impairment of long-lived assets | G24: ='Imput Historical'!G24 -> 0 | H24: ='Imput Historical'!H24 -> -24585 | I24: ='Imput Historical'!I24 -> 4207 | J24: ='Imput Historical'!J24 -> -38252 | K24: 0 | L24: 0 | M24: 0 | N24: 0 | O24: 0
B26: Adjusted EBITDA (excl. other operating income / expenses) | G26: =G27-G14-G15-G24-G22-G23 -> 740632 | H26: =H27-H14-H15-H24-H22-H23 -> 755927 | I26: =I27-I14-I15-I24-I22-I23 -> 1039586 | J26: =J27-J14-J15-J24-J22-J23 -> 1576590 | K26: =K27-K14-K15-K24-K22-K23 -> 2316875.8 | L26: =L27-L14-L15-L24-L22-L23 -> 2505955.8 | M26: =M27-M14-M15-M24-M22-M23 -> 2695338.1 | N26: =N27-N14-N15-N24-N22-N23 -> 2844854.7 | O26: =O27-O14-O15-O24-O22-O23 -> 2903539.2
B27: EBIT / Operating profit | G27: =G17+G19+G20+G21+G22+G23+G24 -> 529147 | H27: =H17+H19+H20+H21+H22+H23+H24 -> 631487 | I27: =I17+I19+I20+I21+I22+I23+I24 -> 625390 | J27: =J17+J19+J20+J21+J22+J23+J24 -> 1250830 | K27: =K17+K19+K20+K21+K22+K23+K24 -> 1468610.4 | L27: =L17+L19+L20+L21+L22+L23+L24 -> 1555898.5 | M27: =M17+M19+M20+M21+M22+M23+M24 -> 1650275.1 | N27: =N17+N19+N20+N21+N22+N23+N24 -> 1716186.7 | O27: =O17+O19+O20+O21+O22+O23+O24 -> 1707151.1
B29: Income (loss) from investments in associates | G29: ='Imput Historical'!G28 -> 0 | H29: ='Imput Historical'!H28 -> 0 | I29: ='Imput Historical'!I28 -> 0 | J29: ='Imput Historical'!J28 -> -5214 | K29: 0 | L29: 0 | M29: 0 | N29: 0 | O29: 0
B30: Interest income | G30: ='Imput Historical'!G29 -> 809 | H30: ='Imput Historical'!H29 -> 1235 | I30: ='Imput Historical'!I29 -> 4535 | J30: ='Imput Historical'!J29 -> 10594 | K30: =K173 -> 16152.06 | L30: =L173 -> 9378.7812 | M30: =M173 -> 10453.293 | N30: =N173 -> 19940.393 | O30: =O173 -> 37153.748
B31: Interest expense | G31: ='Imput Historical'!G30 -> -28886 | H31: ='Imput Historical'!H30 -> -21879 | I31: ='Imput Historical'!I30 -> -62499 | J31: ='Imput Historical'!J30 -> -163356 | K31: =K172 -> -236555.77 | L31: =L172 -> -210305.77 | M31: =M172 -> -184055.77 | N31: =N172 -> -157805.77 | O31: =O172 -> -131555.77
B32: Other financial income (expense) | G32: ='Imput Historical'!G31 -> -67556 | H32: ='Imput Historical'!H31 -> -65484 | I32: ='Imput Historical'!I31 -> 23401 | J32: ='Imput Historical'!J31 -> -88183 | K32: 0 | L32: 0 | M32: 0 | N32: 0 | O32: 0
B34: Financial income (expense), net | G34: =SUM(G30:G32) -> -95633 | H34: =SUM(H30:H32) -> -86128 | I34: =SUM(I30:I32) -> -34563 | J34: =SUM(J30:J32) -> -240945 | K34: =SUM(K30:K32) -> -220403.71 | L34: =SUM(L30:L32) -> -200926.99 | M34: =SUM(M30:M32) -> -173602.48 | N34: =SUM(N30:N32) -> -137865.38 | O34: =SUM(O30:O32) -> -94402.027
B36: Profit before income tax | G36: =G27+G29+G34 -> 433514 | H36: =H27+H29+H34 -> 545359 | I36: =I27+I29+I34 -> 590827 | J36: =J27+J29+J34 -> 1004671 | K36: =K27+K29+K34 -> 1248206.7 | L36: =L27+L29+L34 -> 1354971.6 | M36: =M27+M29+M34 -> 1476672.6 | N36: =N27+N29+N34 -> 1578321.3 | O36: =O27+O29+O34 -> 1612749
B38: Current income tax (expense) | G38: ='Imput Historical'!G37 -> -92089 | H38: ='Imput Historical'!H37 -> -16393 | I38: ='Imput Historical'!I37 -> -426288 | J38: ='Imput Historical'!J37 -> -241657 | K38: =-K36*'Imputs Drivers'!G38 -> -374462.01 | L38: =-L36*'Imputs Drivers'!H38 -> -406491.47 | M38: =-M36*'Imputs Drivers'!I38 -> -443001.78 | N38: =-N36*'Imputs Drivers'!J38 -> -473496.39 | O38: =-O36*'Imputs Drivers'!K38 -> -483824.71
B39: Deferred income tax (expense) benefit | G39: ='Imput Historical'!G38 -> -71890 | H39: ='Imput Historical'!H38 -> -132011 | I39: ='Imput Historical'!I38 -> 312982 | J39: ='Imput Historical'!J38 -> -43951 | K39: 0 | L39: 0 | M39: 0 | N39: 0 | O39: 0
B40: Income tax (expense) | G40: =G38+G39 -> -163979 | H40: =H38+H39 -> -148404 | I40: =I38+I39 -> -113306 | J40: =J38+J39 -> -285608 | K40: =K38+K39 -> -374462.01 | L40: =L38+L39 -> -406491.47 | M40: =M38+M39 -> -443001.78 | N40: =N38+N39 -> -473496.39 | O40: =O38+O39 -> -483824.71
B42: Profit for the year, net | G42: =G36+G40 -> 269535 | H42: =H36+H40 -> 396955 | I42: =I36+I40 -> 477521 | J42: =J36+J40 -> 719063 | K42: =K36+K40 -> 873744.69 | L42: =L36+L40 -> 948480.09 | M42: =M36+M40 -> 1033670.8 | N42: =N36+N40 -> 1104824.9 | O42: =O36+O40 -> 1128924.3
B44: Earnings per share
B46: Basic (USD per share) | G46: ='Imput Historical'!G54 -> 3.068 | H46: ='Imput Historical'!H54 -> 4.237 | I46: ='Imput Historical'!I54 -> 4.979 | J46: ='Imput Historical'!J54 -> 7.015 | K46: =K42*$J$46/$J$42 -> 8.5240361 | L46: =L42*$J$46/$J$42 -> 9.2531361 | M46: =M42*$J$46/$J$42 -> 10.084236 | N46: =N42*$J$46/$J$42 -> 10.778397 | O46: =O42*$J$46/$J$42 -> 11.013505
B47: Diluted (USD per share) | G47: ='Imput Historical'!G55 -> 2.755 | H47: ='Imput Historical'!H55 -> 4 | I47: ='Imput Historical'!I55 -> 4.633 | J47: ='Imput Historical'!J55 -> 6.707 | K47: =K42*$J$47/$J$42 -> 8.1497805 | L47: =L42*$J$47/$J$42 -> 8.8468687 | M47: =M42*$J$47/$J$42 -> 9.641478 | N47: =N42*$J$47/$J$42 -> 10.305162 | O47: =O42*$J$47/$J$42 -> 10.529947
B50: BALANCE SHEET
B52: Amounts expressed in thousands of US Dollars | G52: 2022A | H52: 2023A | I52: 2024A | J52: 2025A | K52: 2026E | L52: 2027E | M52: 2028E | N52: 2029E | O52: 2030E
B54: Assets
B55: Noncurrent assets
B57: Property, plant and equipment | G57: ='Imput Historical'!G154 -> 1606339 | H57: ='Imput Historical'!H154 -> 1927759 | I57: ='Imput Historical'!I154 -> 2805983 | J57: ='Imput Historical'!J154 -> 5543032 | K57: =J57+'Imputs Drivers'!G26*1000+K14 -> 6244766.6 | L57: =K57+'Imputs Drivers'!H26*1000+L14 -> 6794709.3 | M57: =L57+'Imputs Drivers'!I26*1000+M14 -> 7149646.3 | N57: =M57+'Imputs Drivers'!J26*1000+N14 -> 7320978.2 | O57: =N57+'Imputs Drivers'!K26*1000+O14 -> 7324590.1
B58: Goodwill | G58: ='Imput Historical'!G155 -> 28288 | H58: ='Imput Historical'!H155 -> 22576 | I58: ='Imput Historical'!I155 -> 22576 | J58: ='Imput Historical'!J155 -> 22576 | K58: =J58 -> 22576 | L58: =K58 -> 22576 | M58: =L58 -> 22576 | N58: =M58 -> 22576 | O58: =N58 -> 22576
B59: Other intangible assets | G59: ='Imput Historical'!G156 -> 6792 | H59: ='Imput Historical'!H156 -> 10026 | I59: ='Imput Historical'!I156 -> 15443 | J59: ='Imput Historical'!J156 -> 18485 | K59: =J59 -> 18485 | L59: =K59 -> 18485 | M59: =L59 -> 18485 | N59: =M59 -> 18485 | O59: =N59 -> 18485
B60: Right-of-use assets | G60: ='Imput Historical'!G157 -> 26228 | H60: ='Imput Historical'!H157 -> 61025 | I60: ='Imput Historical'!I157 -> 105333 | J60: ='Imput Historical'!J157 -> 153283 | K60: =J60 -> 153283 | L60: =K60 -> 153283 | M60: =L60 -> 153283 | N60: =M60 -> 153283 | O60: =N60 -> 153283
B61: Biological assets | G61: ='Imput Historical'!G158 -> 0 | H61: ='Imput Historical'!H158 -> 0 | I61: ='Imput Historical'!I158 -> 10027 | J61: ='Imput Historical'!J158 -> 15855 | K61: =J61 -> 15855 | L61: =K61 -> 15855 | M61: =L61 -> 15855 | N61: =M61 -> 15855 | O61: =N61 -> 15855
B62: Investments in associates | G62: ='Imput Historical'!G159 -> 6443 | H62: ='Imput Historical'!H159 -> 8619 | I62: ='Imput Historical'!I159 -> 11906 | J62: ='Imput Historical'!J159 -> 54542 | K62: =J62 -> 54542 | L62: =K62 -> 54542 | M62: =L62 -> 54542 | N62: =M62 -> 54542 | O62: =N62 -> 54542
B63: Trade and other receivables (NC) | G63: ='Imput Historical'!G160 -> 15864 | H63: ='Imput Historical'!H160 -> 136351 | I63: ='Imput Historical'!I160 -> 205268 | J63: ='Imput Historical'!J160 -> 373026 | K63: =K7*($J$63/$J$7) -> 534652.37 | L63: =L7*($J$63/$J$7) -> 577676.16 | M63: =M7*($J$63/$J$7) -> 619945.15 | N63: =N7*($J$63/$J$7) -> 652802.24 | O63: =O7*($J$63/$J$7) -> 665356.13
B64: Deferred income tax assets | G64: ='Imput Historical'!G161 -> 335 | H64: ='Imput Historical'!H161 -> 5743 | I64: ='Imput Historical'!I161 -> 3565 | J64: ='Imput Historical'!J161 -> 36514 | K64: =J64 -> 36514 | L64: =K64 -> 36514 | M64: =L64 -> 36514 | N64: =M64 -> 36514 | O64: =N64 -> 36514
B66: Total noncurrent assets | G66: =SUM(G57:G64) -> 1690289 | H66: =SUM(H57:H64) -> 2172099 | I66: =SUM(I57:I64) -> 3180101 | J66: =SUM(J57:J64) -> 6217313 | K66: =SUM(K57:K64) -> 7080673.9 | L66: =SUM(L57:L64) -> 7673640.4 | M66: =SUM(M57:M64) -> 8070846.4 | N66: =SUM(N57:N64) -> 8275035.5 | O66: =SUM(O57:O64) -> 8291201.2
B68: Current assets
B70: Inventories | G70: ='Imput Historical'!G166 -> 12899 | H70: ='Imput Historical'!H166 -> 7549 | I70: ='Imput Historical'!I166 -> 6469 | J70: ='Imput Historical'!J166 -> 9457 | K70: =K7*($J$70/$J$7) -> 13554.571 | L70: =L7*($J$70/$J$7) -> 14645.315 | M70: =M7*($J$70/$J$7) -> 15716.924 | N70: =N7*($J$70/$J$7) -> 16549.921 | O70: =O7*($J$70/$J$7) -> 16868.189
B71: Trade and other receivables | G71: ='Imput Historical'!G167 -> 90406 | H71: ='Imput Historical'!H167 -> 205102 | I71: ='Imput Historical'!I167 -> 281495 | J71: ='Imput Historical'!J167 -> 347681 | K71: =K7*($J$71/$J$7) -> 498325.77 | L71: =L7*($J$71/$J$7) -> 538426.34 | M71: =M7*($J$71/$J$7) -> 577823.39 | N71: =N7*($J$71/$J$7) -> 608448.03 | O71: =O7*($J$71/$J$7) -> 620148.95
B72: Cash, bank balances and other short-term investments | G72: ='Imput Historical'!G168 -> 244385 | H72: ='Imput Historical'!H168 -> 213253 | I72: ='Imput Historical'!I168 -> 764307 | J72: ='Imput Historical'!J168 -> 538402 | K72: =K149 -> 312626.04 | L72: =L149 -> 348443.09 | M72: =M149 -> 664679.76 | N72: =N149 -> 1238458.3 | O72: =O149 -> 2010059.1
B74: Total current assets | G74: =SUM(G70:G72) -> 347690 | H74: =SUM(H70:H72) -> 425904 | I74: =SUM(I70:I72) -> 1052271 | J74: =SUM(J70:J72) -> 895540 | K74: =SUM(K70:K72) -> 824506.39 | L74: =SUM(L70:L72) -> 901514.75 | M74: =SUM(M70:M72) -> 1258220.1 | N74: =SUM(N70:N72) -> 1863456.2 | O74: =SUM(O70:O72) -> 2647076.2
B75: Total assets | G75: =G66+G74 -> 2037979 | H75: =H66+H74 -> 2598003 | I75: =I66+I74 -> 4232372 | J75: =J66+J74 -> 7112853 | K75: =K66+K74 -> 7905180.3 | L75: =L66+L74 -> 8575155.2 | M75: =M66+M74 -> 9329066.5 | N75: =N66+N74 -> 10138492 | O75: =O66+O74 -> 10938277
B77: Equity and liabilities
B78: Equity
B80: Capital stock | G80: ='Imput Historical'!G176 -> 517873 | H80: ='Imput Historical'!H176 -> 517874 | I80: ='Imput Historical'!I176 -> 398064 | J80: ='Imput Historical'!J176 -> 491165 | K80: =J80 -> 491165 | L80: =K80 -> 491165 | M80: =L80 -> 491165 | N80: =M80 -> 491165 | O80: =N80 -> 491165
B81: Other equity instruments | G81: ='Imput Historical'!G177 -> 32144 | H81: ='Imput Historical'!H177 -> 32144 | I81: ='Imput Historical'!I177 -> 32144 | J81: ='Imput Historical'!J177 -> 32144 | K81: =J81 -> 32144 | L81: =K81 -> 32144 | M81: =L81 -> 32144 | N81: =M81 -> 32144 | O81: =N81 -> 32144
B82: Legal reserve | G82: ='Imput Historical'!G178 -> 2603 | H82: ='Imput Historical'!H178 -> 8233 | I82: ='Imput Historical'!I178 -> 8233 | J82: ='Imput Historical'!J178 -> 8233 | K82: =J82 -> 8233 | L82: =K82 -> 8233 | M82: =L82 -> 8233 | N82: =M82 -> 8233 | O82: =N82 -> 8233
B83: Share-based payments | G83: ='Imput Historical'!G179 -> 40744 | H83: ='Imput Historical'!H179 -> 42476 | I83: ='Imput Historical'!I179 -> 45628 | J83: ='Imput Historical'!J179 -> -32765 | K83: =J83 -> -32765 | L83: =K83 -> -32765 | M83: =L83 -> -32765 | N83: =M83 -> -32765 | O83: =N83 -> -32765
B84: Share repurchase reserve | G84: ='Imput Historical'!G180 -> 49465 | H84: ='Imput Historical'!H180 -> 79324 | I84: ='Imput Historical'!I180 -> 129324 | J84: ='Imput Historical'!J180 -> 179324 | K84: =J84 -> 179324 | L84: =K84 -> 179324 | M84: =L84 -> 179324 | N84: =M84 -> 179324 | O84: =N84 -> 179324
B85: Other accumulated comprehensive income (losses) | G85: ='Imput Historical'!G181 -> -8694 | H85: ='Imput Historical'!H181 -> -4427 | I85: ='Imput Historical'!I181 -> -11057 | J85: ='Imput Historical'!J181 -> -11034 | K85: =J85 -> -11034 | L85: =K85 -> -11034 | M85: =L85 -> -11034 | N85: =M85 -> -11034 | O85: =N85 -> -11034
B86: Accumulated profit (losses) | G86: ='Imput Historical'!G182 -> 209925 | H86: ='Imput Historical'!H182 -> 571391 | I86: ='Imput Historical'!I182 -> 1018877 | J86: ='Imput Historical'!J182 -> 1844527 | K86: =J86+K42 -> 2718271.7 | L86: =K86+L42 -> 3666751.8 | M86: =L86+M42 -> 4700422.6 | N86: =M86+N42 -> 5805247.5 | O86: =N86+O42 -> 6934171.8
B88: Total equity | G88: =SUM(G80:G86) -> 844060 | H88: =SUM(H80:H86) -> 1247015 | I88: =SUM(I80:I86) -> 1621213 | J88: =SUM(J80:J86) -> 2511594 | K88: =SUM(K80:K86) -> 3385338.7 | L88: =SUM(L80:L86) -> 4333818.8 | M88: =SUM(M80:M86) -> 5367489.6 | N88: =SUM(N80:N86) -> 6472314.5 | O88: =SUM(O80:O86) -> 7601238.8
B90: Liabilities
B91: Noncurrent liabilities
B93: Deferred income tax liabilities | G93: ='Imput Historical'!G189 -> 243411 | H93: ='Imput Historical'!H189 -> 383128 | I93: ='Imput Historical'!I189 -> 64398 | J93: ='Imput Historical'!J189 -> 298664 | K93: =J93 -> 298664 | L93: =K93 -> 298664 | M93: =L93 -> 298664 | N93: =M93 -> 298664 | O93: =N93 -> 298664
B94: Lease liabilities (NC) | G94: ='Imput Historical'!G190 -> 20644 | H94: ='Imput Historical'!H190 -> 35600 | I94: ='Imput Historical'!I190 -> 37638 | J94: ='Imput Historical'!J190 -> 88451 | K94: =J94 -> 88451 | L94: =K94 -> 88451 | M94: =L94 -> 88451 | N94: =M94 -> 88451 | O94: =N94 -> 88451
B95: Provisions (NC) | G95: ='Imput Historical'!G191 -> 31668 | H95: ='Imput Historical'!H191 -> 12339 | I95: ='Imput Historical'!I191 -> 33058 | J95: ='Imput Historical'!J191 -> 51513 | K95: =J95 -> 51513 | L95: =K95 -> 51513 | M95: =L95 -> 51513 | N95: =M95 -> 51513 | O95: =N95 -> 51513
B96: Borrowings (NC) | G96: ='Imput Historical'!G192 -> 477601 | H96: ='Imput Historical'!H192 -> 554832 | I96: ='Imput Historical'!I192 -> 1402343 | J96: ='Imput Historical'!J192 -> 2803982 | K96: =K168-K175 -> 2454077 | L96: =L168-L175 -> 2104077 | M96: =M168-M175 -> 1754077 | N96: =N168-N175 -> 1404077 | O96: =O168-O175 -> 1054077
B97: Employee benefits | G97: ='Imput Historical'!G193 -> 12251 | H97: ='Imput Historical'!H193 -> 5703 | I97: ='Imput Historical'!I193 -> 15968 | J97: ='Imput Historical'!J193 -> 16226 | K97: =J97 -> 16226 | L97: =K97 -> 16226 | M97: =L97 -> 16226 | N97: =M97 -> 16226 | O97: =N97 -> 16226
B98: Income tax liability (NC) | G98: ='Imput Historical'!G194 -> 0 | H98: ='Imput Historical'!H194 -> 0 | I98: ='Imput Historical'!I194 -> 0 | J98: ='Imput Historical'!J194 -> 13964 | K98: =J98 -> 13964 | L98: =K98 -> 13964 | M98: =L98 -> 13964 | N98: =M98 -> 13964 | O98: =N98 -> 13964
B99: Trade and other payables (NC) | G99: ='Imput Historical'!G195 -> 0 | H99: ='Imput Historical'!H195 -> 0 | I99: ='Imput Historical'!I195 -> 0 | J99: ='Imput Historical'!J195 -> 292236 | K99: =J99 -> 292236 | L99: =K99 -> 292236 | M99: =L99 -> 292236 | N99: =M99 -> 292236 | O99: =N99 -> 292236
B101: Total noncurrent liabilities | G101: =SUM(G93:G99) -> 785575 | H101: =SUM(H93:H99) -> 991602 | I101: =SUM(I93:I99) -> 1553405 | J101: =SUM(J93:J99) -> 3565036 | K101: =SUM(K93:K99) -> 3215131 | L101: =SUM(L93:L99) -> 2865131 | M101: =SUM(M93:M99) -> 2515131 | N101: =SUM(N93:N99) -> 2165131 | O101: =SUM(O93:O99) -> 1815131
B103: Current liabilities
B105: Provisions (C) | G105: ='Imput Historical'!G201 -> 2848 | H105: ='Imput Historical'!H201 -> 4133 | I105: ='Imput Historical'!I201 -> 3910 | J105: ='Imput Historical'!J201 -> 10800 | K105: =J105 -> 10800 | L105: =K105 -> 10800 | M105: =L105 -> 10800 | N105: =M105 -> 10800 | O105: =N105 -> 10800
B106: Lease liabilities (C) | G106: ='Imput Historical'!G202 -> 8550 | H106: ='Imput Historical'!H202 -> 34868 | I106: ='Imput Historical'!I202 -> 58022 | J106: ='Imput Historical'!J202 -> 55452 | K106: =J106 -> 55452 | L106: =K106 -> 55452 | M106: =L106 -> 55452 | N106: =M106 -> 55452 | O106: =N106 -> 55452
B107: Borrowings (C) | G107: ='Imput Historical'!G203 -> 71731 | H107: ='Imput Historical'!H203 -> 61223 | I107: ='Imput Historical'!I203 -> 46224 | J107: ='Imput Historical'!J203 -> 350095 | K107: =K175+K180 -> 350000 | L107: =L175+L180 -> 350000 | M107: =M175+M180 -> 350000 | N107: =N175+N180 -> 350000 | O107: =O175+O180 -> 350000
B108: Salaries and payroll taxes | G108: ='Imput Historical'!G204 -> 25120 | H108: ='Imput Historical'!H204 -> 17555 | I108: ='Imput Historical'!I204 -> 32656 | J108: ='Imput Historical'!J204 -> 35891 | K108: =K7*($J$108/$J$7) -> 51442.012 | L108: =L7*($J$108/$J$7) -> 55581.581 | M108: =M7*($J$108/$J$7) -> 59648.526 | N108: =N7*($J$108/$J$7) -> 62809.898 | O108: =O7*($J$108/$J$7) -> 64017.781
B109: Income tax liability (C) | G109: ='Imput Historical'!G205 -> 58770 | H109: ='Imput Historical'!H205 -> 3 | I109: ='Imput Historical'!I205 -> 382041 | J109: ='Imput Historical'!J205 -> 120910 | K109: =K7*($J$109/$J$7) -> 173298.42 | L109: =L7*($J$109/$J$7) -> 187243.85 | M109: =M7*($J$109/$J$7) -> 200944.62 | N109: =N7*($J$109/$J$7) -> 211594.68 | O109: =O7*($J$109/$J$7) -> 215663.81
B110: Other taxes and royalties | G110: ='Imput Historical'!G206 -> 20312 | H110: ='Imput Historical'!H206 -> 36549 | I110: ='Imput Historical'!I206 -> 47715 | J110: ='Imput Historical'!J206 -> 43945 | K110: =K7*($J$110/$J$7) -> 62985.685 | L110: =L7*($J$110/$J$7) -> 68054.181 | M110: =M7*($J$110/$J$7) -> 73033.755 | N110: =N7*($J$110/$J$7) -> 76904.544 | O110: =O7*($J$110/$J$7) -> 78383.477
B111: Trade and other payables (C) | G111: ='Imput Historical'!G207 -> 221013 | H111: ='Imput Historical'!H207 -> 205055 | I111: ='Imput Historical'!I207 -> 487186 | J111: ='Imput Historical'!J207 -> 419130 | K111: =K7*($J$111/$J$7) -> 600732.51 | L111: =L7*($J$111/$J$7) -> 649073.81 | M111: =M7*($J$111/$J$7) -> 696567.02 | N111: =N7*($J$111/$J$7) -> 733485.07 | O111: =O7*($J$111/$J$7) -> 747590.55
B113: Total current liabilities | G113: =SUM(G105:G111) -> 408344 | H113: =SUM(H105:H111) -> 359386 | I113: =SUM(I105:I111) -> 1057754 | J113: =SUM(J105:J111) -> 1036223 | K113: =SUM(K105:K111) -> 1304710.6 | L113: =SUM(L105:L111) -> 1376205.4 | M113: =SUM(M105:M111) -> 1446445.9 | N113: =SUM(N105:N111) -> 1501046.2 | O113: =SUM(O105:O111) -> 1521907.6
B114: Total liabilities | G114: =G101+G113 -> 1193919 | H114: =H101+H113 -> 1350988 | I114: =I101+I113 -> 2611159 | J114: =J101+J113 -> 4601259 | K114: =K101+K113 -> 4519841.6 | L114: =L101+L113 -> 4241336.4 | M114: =M101+M113 -> 3961576.9 | N114: =N101+N113 -> 3666177.2 | O114: =O101+O113 -> 3337038.6
B115: Total equity and liabilities | G115: =G88+G114 -> 2037979 | H115: =H88+H114 -> 2598003 | I115: =I88+I114 -> 4232372 | J115: =J88+J114 -> 7112853 | K115: =K88+K114 -> 7905180.3 | L115: =L88+L114 -> 8575155.2 | M115: =M88+M114 -> 9329066.5 | N115: =N88+N114 -> 10138492 | O115: =O88+O114 -> 10938277
B117: BS CHECK (must = 0) | G117: =G75-G115 -> 0 | H117: =H75-H115 -> 0 | I117: =I75-I115 -> 0 | J117: =J75-J115 -> 0 | K117: =K75-K115 -> 0 | L117: =L75-L115 -> 0 | M117: =M75-M115 -> 0 | N117: =N75-N115 -> 0 | O117: =O75-O115 -> 0
B120: CASH FLOW STATEMENT
B122: Amounts expressed in thousands of US Dollars | G122: 2022A | H122: 2023A | I122: 2024A | J122: 2025A | K122: 2026E | L122: 2027E | M122: 2028E | N122: 2029E | O122: 2030E
B124: Cash flows from operating activities:
B125: Profit for the year, net | G125: =G42 -> 269535 | H125: =H42 -> 396955 | I125: =I42 -> 477521 | J125: =J42 -> 719063 | K125: =K42 -> 873744.69 | L125: =L42 -> 948480.09 | M125: =M42 -> 1033670.8 | N125: =N42 -> 1104824.9 | O125: =O42 -> 1128924.3
B126: D&A addback | G126: =-G14 -> 234862 | H126: =-H14 -> 276430 | I126: =-I14 -> 437699 | J126: =-J14 -> 738903 | K126: =-K14 -> 848265.43 | L126: =-L14 -> 950057.28 | M126: =-M14 -> 1045063 | N126: =-N14 -> 1128668 | O126: =-O14 -> 1196388.1
B127: Other non-cash addback | G127: =-G15 -> 0 | H127: =-H15 -> 27539 | I127: =-I15 -> 33570 | J127: =-J15 -> 29016 | K127: =-K15 -> 0 | L127: =-L15 -> 0 | M127: =-M15 -> 0 | N127: =-N15 -> 0 | O127: =-O15 -> 0
B128: Working capital & other changes | G128: =G130-G125-G126-G127 -> 185374 | H128: =H130-H125-H126-H127 -> 11109 | I128: =I130-I125-I126-I127 -> 10236 | J128: =J130-J125-J126-J127 -> -690791 | K128: =-(K63-J63)-(K70-J70)-(K71-J71)+(K108-J108)+(K109-J109)+(K110-J110)+(K111-J111) -> -47786.076 | L128: =-(L63-K63)-(L70-K70)-(L71-K71)+(L108-K108)+(L109-K109)+(L110-K110)+(L111-K111) -> -12720.314 | M128: =-(M63-L63)-(M70-L70)-(M71-L71)+(M108-L108)+(M109-L109)+(M110-L110)+(M111-L111) -> -12497.15 | N128: =-(N63-M63)-(N70-M70)-(N71-M71)+(N108-M108)+(N109-M109)+(N110-M110)+(N111-M111) -> -9714.4517 | O128: =-(O63-N63)-(O70-N70)-(O71-N71)+(O108-N108)+(O109-N109)+(O110-N110)+(O111-N111) -> -3711.6537
B130: Net cash flows from operating activities (CFO) | G130: ='Imput Historical'!G106 -> 689771 | H130: ='Imput Historical'!H106 -> 712033 | I130: ='Imput Historical'!I106 -> 959026 | J130: ='Imput Historical'!J106 -> 796191 | K130: =SUM(K125:K128) -> 1674224 | L130: =SUM(L125:L128) -> 1885817.1 | M130: =SUM(M125:M128) -> 2066236.7 | N130: =SUM(N125:N128) -> 2223778.5 | O130: =SUM(O125:O128) -> 2321600.8
B132: Cash flows from investing activities:
B133: Capital expenditures (CapEx) | G133: ='Imput Historical'!G109 -> -479025 | H133: ='Imput Historical'!H109 -> -688437 | I133: ='Imput Historical'!I109 -> -1052530 | J133: ='Imput Historical'!J109 -> -1455411 | K133: =-'Imputs Drivers'!G26*1000 -> -1550000 | L133: =-'Imputs Drivers'!H26*1000 -> -1500000 | M133: =-'Imputs Drivers'!I26*1000 -> -1400000 | N133: =-'Imputs Drivers'!J26*1000 -> -1300000 | O133: =-'Imputs Drivers'!K26*1000 -> -1200000
B134: Other investing activities | G134: =G136-G133 -> -103687 | H134: =H136-H133 -> -10876 | I134: =I136-I133 -> 654 | J134: =J136-J133 -> -893653 | K134: 0 | L134: 0 | M134: 0 | N134: 0 | O134: 0
B136: Net cash flows from investing activities (CFI) | G136: ='Imput Historical'!G119 -> -582712 | H136: ='Imput Historical'!H119 -> -699313 | I136: ='Imput Historical'!I119 -> -1051876 | J136: ='Imput Historical'!J119 -> -2349064 | K136: =K133+K134 -> -1550000 | L136: =L133+L134 -> -1500000 | M136: =M133+M134 -> -1400000 | N136: =N133+N134 -> -1300000 | O136: =O133+O134 -> -1200000
B138: Cash flows from financing activities:
B139: Proceeds from borrowings | G139: ='Imput Historical'!G122 -> 128788 | H139: ='Imput Historical'!H122 -> 318169 | I139: ='Imput Historical'!I122 -> 1320897 | J139: ='Imput Historical'!J122 -> 2838173 | K139: =K167 -> 0 | L139: =L167 -> 0 | M139: =M167 -> 0 | N139: =N167 -> 0 | O139: =O167 -> 0
B140: Repayment of borrowings | G140: ='Imput Historical'!G123 -> -195091 | H140: ='Imput Historical'!H123 -> -211499 | I140: ='Imput Historical'!I123 -> -470351 | J140: ='Imput Historical'!J123 -> -1173623 | K140: =K166 -> -350000 | L140: =L166 -> -350000 | M140: =M166 -> -350000 | N140: =N166 -> -350000 | O140: =O166 -> -350000
B141: Interest on borrowings (included in CFO) | G141: ='Imput Historical'!G124 -> -34430 | H141: ='Imput Historical'!H124 -> -22993 | I141: ='Imput Historical'!I124 -> -53897 | J141: ='Imput Historical'!J124 -> -148310 | K141: 0 | L141: 0 | M141: 0 | N141: 0 | O141: 0
B142: Other financing activities | G142: =G144-G139-G140-G141 -> -42468 | H142: =H144-H139-H140-H141 -> -64121 | I142: =I144-I139-I140-I141 -> -155438 | J142: =J144-J139-J140-J141 -> -188700 | K142: =K179 -> 0 | L142: =L179 -> 0 | M142: =M179 -> 0 | N142: =N179 -> 0 | O142: =O179 -> 0
B144: Net cash flows from financing activities (CFF) | G144: ='Imput Historical'!G131 -> -143201 | H144: ='Imput Historical'!H131 -> 19556 | I144: ='Imput Historical'!I131 -> 641211 | J144: ='Imput Historical'!J131 -> 1327540 | K144: =SUM(K139:K142) -> -350000 | L144: =SUM(L139:L142) -> -350000 | M144: =SUM(M139:M142) -> -350000 | N144: =SUM(N139:N142) -> -350000 | O144: =SUM(O139:O142) -> -350000
...
